watchfiles-1.0.2.dist-info/METADATA
watchfiles-1.0.2.dist-info/WHEEL
watchfiles-1.0.2.dist-info/entry_points.txt
watchfiles-1.0.2.dist-info/licenses/LICENSE
watchfiles.libs/libgcc_s-1e52349c.so.1
watchfiles/main.py
watchfiles/_rust_notify.pyi
watchfiles/run.py
watchfiles/__init__.py
watchfiles/cli.py
watchfiles/version.py
watchfiles/__main__.py
watchfiles/filters.py
watchfiles/py.typed
watchfiles/_rust_notify.cpython-313-x86_64-linux-musl.so
watchfiles-1.0.2.dist-info/RECORD
