Metadata-Version: 2.4
Name: watchfiles
Version: 1.0.2
Classifier: Development Status :: 5 - Production/Stable
Classifier: Environment :: Console
Classifier: Programming Language :: Python
Classifier: Programming Language :: Python :: 3
Classifier: Programming Language :: Python :: 3 :: Only
Classifier: Programming Language :: Python :: 3.9
Classifier: Programming Language :: Python :: 3.10
Classifier: Programming Language :: Python :: 3.11
Classifier: Programming Language :: Python :: 3.12
Classifier: Programming Language :: Python :: 3.13
Classifier: Intended Audience :: Developers
Classifier: Intended Audience :: Information Technology
Classifier: Intended Audience :: System Administrators
Classifier: License :: OSI Approved :: MIT License
Classifier: Operating System :: POSIX :: Linux
Classifier: Operating System :: Microsoft :: Windows
Classifier: Operating System :: MacOS
Classifier: Environment :: MacOS X
Classifier: Topic :: Software Development :: Libraries :: Python Modules
Classifier: Topic :: System :: Filesystems
Classifier: Framework :: AnyIO
Requires-Dist: anyio >=3.0.0
License-File: LICENSE
Summary: Simple, modern and high performance file watching and code reload in python.
Home-Page: https://github.com/samuelcolvin/watchfiles
Author-email: Samuel Colvin <s@muelcolvin.com>
License: MIT
Requires-Python: >=3.9
Project-URL: Homepage, https://github.com/samuelcolvin/watchfiles
Project-URL: Documentation, https://watchfiles.helpmanual.io
Project-URL: Funding, https://github.com/sponsors/samuelcolvin
Project-URL: Source, https://github.com/samuelcolvin/watchfiles
Project-URL: Changelog, https://github.com/samuelcolvin/watchfiles/releases
